zyzyida_mcp_demo/__init__.py
zyzyida_mcp_demo-0.1.0.dist-info/METADATA
zyzyida_mcp_demo-0.1.0.dist-info/WHEEL
zyzyida_mcp_demo-0.1.0.dist-info/entry_points.txt
zyzyida_mcp_demo-0.1.0.dist-info/RECORD
